pyviztest/__init__.py
pyviztest/pyviztestmain.py
pyviztest/viztest.py
pyviztest-1.0.0.dist-info/LICENSE
pyviztest-1.0.0.dist-info/METADATA
pyviztest-1.0.0.dist-info/WHEEL
pyviztest-1.0.0.dist-info/top_level.txt
pyviztest-1.0.0.dist-info/RECORD
