Metadata-Version: 2.1
Name: pyviztest
Version: 1.0.0
Summary: A Visual Testing Library in Python. Works with Playwright and Selenium. Can be integrated with Allure Report.
Author: sanosuke009
Project-URL: Homepage, https://github.com/sanosuke009/pyviztest
Project-URL: Bug Tracker, https://github.com/sanosuke009/pyviztest/issues
Classifier: Programming Language :: Python :: 3
Classifier: License :: OSI Approved :: MIT License
Classifier: Operating System :: OS Independent
Requires-Python: >=3.7
License-File: LICENSE
Requires-Dist: selenium (>=4.8.0)
Requires-Dist: playwright (>=1.32.1)
Requires-Dist: Pillow (>=9.5.0)
Requires-Dist: pixelmatch (>=0.3.0)
Requires-Dist: allure-pytest (>=2.13.1)
